dotenv_vault/__init__.py
dotenv_vault/__version__.py
dotenv_vault/main.py
dotenv_vault/test_vault.py
python_dotenv_vault-0.7.0.dist-info/licenses/LICENSE
python_dotenv_vault-0.7.0.dist-info/METADATA
python_dotenv_vault-0.7.0.dist-info/WHEEL
python_dotenv_vault-0.7.0.dist-info/top_level.txt
python_dotenv_vault-0.7.0.dist-info/RECORD
