Metadata-Version: 2.4
Name: python-dotenv-vault
Version: 0.7.0
Summary: Decrypt .env.vault file.
Home-page: https://github.com/dotenv-org/python-dotenv-vault
Author: dotenv
Author-email: mot@dotenv.org
License: MIT
Keywords: environment,environment variables,deployments,settings,env,dotenv,configurations,python,dotenv-vault
License-File: LICENSE
Requires-Dist: python-dotenv>=0.21.0
Requires-Dist: cryptography>=41.0.0
Dynamic: author
Dynamic: author-email
Dynamic: description
Dynamic: description-content-type
Dynamic: home-page
Dynamic: keywords
Dynamic: license
Dynamic: license-file
Dynamic: requires-dist
Dynamic: summary
